test3_pycon/__init__.py
test3_pycon/__main__.py
test3_pycon-0.0.2.data/scripts/hello
test3_pycon-0.0.2.dist-info/METADATA
test3_pycon-0.0.2.dist-info/WHEEL
test3_pycon-0.0.2.dist-info/entry_points.txt
test3_pycon-0.0.2.dist-info/top_level.txt
test3_pycon-0.0.2.dist-info/RECORD
